{
    "Address": "1xxxxx",
    "AddressIPVersion": "ipv4",
    "AddressType": "intranet",
    "Bandwidth": 5120,
    "CreateTime": "2022-07-20T15:29Z",
    "CreateTimeStamp": 1658302171000,
    "InternetChargeType": "4",
    "InternetChargeTypeAlias": "paybytraffic",
    "LoadBalancerId": "lb-xxxxx",
    "LoadBalancerName": "xxxxxslb",
    "LoadBalancerSpec": "slb.s1.small",
    "LoadBalancerStatus": "active",
    "MasterZoneId": "cn-hangzhou-j",
    "NetworkType": "vpc",
    "PayType": "PrePay",
    "RegionId": "cn-hangzhou",
    "RegionIdAlias": "cn-hangzhou",
    "ResourceGroupId": "rg-xxx",
    "SlaveZoneId": "cn-hangzhou-k",
    "Tags": {},
    "VSwitchId": "vsw-xxxx",
    "VpcId": "vpc-xxx"
 }